molina-0.0.1.dist-info/METADATA
molina-0.0.1.dist-info/WHEEL
molina/__init__.py
molina/README.md
molina/main.py
molina/molina.cpython-311-darwin.so
molina-0.0.1.dist-info/RECORD
